jac_speech/VERSION
jac_speech/__init__.py
jac_speech/config.py
jac_speech/stt/__init__.py
jac_speech/stt/requirements.txt
jac_speech/stt/stt.py
jac_speech/vc_tts/__init__.py
jac_speech/vc_tts/action_utils.py
jac_speech/vc_tts/models.json
jac_speech/vc_tts/requirements.txt
jac_speech/vc_tts/vc_tts.py
jac_speech/vc_tts/text/__init__.py
jac_speech/vc_tts/text/cleaners.py
jac_speech/vc_tts/text/numbers.py
jac_speech-1.4.2.5.dist-info/METADATA
jac_speech-1.4.2.5.dist-info/WHEEL
jac_speech-1.4.2.5.dist-info/top_level.txt
jac_speech-1.4.2.5.dist-info/RECORD
