Metadata-Version: 2.1
Name: jac_speech
Version: 1.4.2.5
Home-page: https://github.com/Jaseci-Labs/jaseci
Author: Jason Mars
Author-email: jason@jaseci.org
Requires-Dist: jaseci ==1.4.2.5
Requires-Dist: pytest <7.1,>=7.0.1
Requires-Dist: pytest-order <1.1,>=1.0.1
Provides-Extra: all
Requires-Dist: librosa <=0.9.2,>=0.8.0 ; extra == 'all'
Requires-Dist: torch <=2.0.0,>=1.10.2 ; extra == 'all'
Requires-Dist: openai-whisper ==20230314 ; extra == 'all'
Requires-Dist: soundfile <0.13,>=0.12.1 ; extra == 'all'
Requires-Dist: unidecode ==1.3.6 ; extra == 'all'
Requires-Dist: inflect <=6.0.2 ; extra == 'all'
Requires-Dist: numpy >=1.23.0 ; extra == 'all'
Provides-Extra: stt
Requires-Dist: librosa <=0.9.2,>=0.8.0 ; extra == 'stt'
Requires-Dist: torch <=2.0.0,>=1.10.2 ; extra == 'stt'
Requires-Dist: openai-whisper ==20230314 ; extra == 'stt'
Requires-Dist: soundfile <0.13,>=0.12.1 ; extra == 'stt'
Provides-Extra: vc_tts
Requires-Dist: soundfile <0.13,>=0.12.1 ; extra == 'vc_tts'
Requires-Dist: unidecode ==1.3.6 ; extra == 'vc_tts'
Requires-Dist: inflect <=6.0.2 ; extra == 'vc_tts'
Requires-Dist: librosa <=0.9.2,>=0.8.0 ; extra == 'vc_tts'
Requires-Dist: numpy >=1.23.0 ; extra == 'vc_tts'
